aws_ssm/__init__.py
aws_ssm/ssm.py
aws_ssm-0.4.0.dist-info/DESCRIPTION.rst
aws_ssm-0.4.0.dist-info/METADATA
aws_ssm-0.4.0.dist-info/RECORD
aws_ssm-0.4.0.dist-info/WHEEL
aws_ssm-0.4.0.dist-info/metadata.json
aws_ssm-0.4.0.dist-info/top_level.txt
