Metadata-Version: 2.0
Name: aws-ssm
Version: 0.4.0
Summary: Manager that fetches and processes updates for AWS EC2 Systems Manager parameters
Home-page: https://github.com/mixja/aws-ssm
Author: Justin Menga
Author-email: justin.menga@gmail.com
License: ISC
Keywords: aws ssm secrets parameters ec2
Platform: UNKNOWN
Classifier: Development Status :: 4 - Beta
Classifier: Intended Audience :: Developers
Classifier: Programming Language :: Python
Classifier: Programming Language :: Python :: 2
Classifier: Programming Language :: Python :: 2.6
Classifier: Programming Language :: Python :: 2.7
Classifier: Programming Language :: Python :: 3
Classifier: Programming Language :: Python :: 3.3
Classifier: Programming Language :: Python :: 3.4
Classifier: License :: OSI Approved :: ISC License (ISCL)
Provides: aws_ssm
Provides-Extra: test
Requires-Dist: boto3
Provides-Extra: test
Requires-Dist: pytest (>=3.0); extra == 'test'
